kore_plugins_flask_admin/__init__.py
kore_plugins_flask_admin/plugins/__init__.py
kore_plugins_flask_admin/plugins/admin.py
kore_plugins_flask_admin-0.0.1.dist-info/DESCRIPTION.rst
kore_plugins_flask_admin-0.0.1.dist-info/entry_points.txt
kore_plugins_flask_admin-0.0.1.dist-info/METADATA
kore_plugins_flask_admin-0.0.1.dist-info/metadata.json
kore_plugins_flask_admin-0.0.1.dist-info/RECORD
kore_plugins_flask_admin-0.0.1.dist-info/top_level.txt
kore_plugins_flask_admin-0.0.1.dist-info/WHEEL
